pabdas/__init__.py
pabdas/reader.py
pabdas/data/pr1.txt
pabdas/data/pr2.txt
pabdas/data/pr3.txt
pabdas/data/pr4.txt
pabdas/data/pr5.txt
pabdas/data/pr6.txt
pabdas/data/pr7.txt
pabdas/data/pr8.txt
pabdas-0.1.5.dist-info/METADATA
pabdas-0.1.5.dist-info/WHEEL
pabdas-0.1.5.dist-info/top_level.txt
pabdas-0.1.5.dist-info/RECORD
