Metadata-Version: 2.4
Name: pabdas
Version: 0.1.5
Summary: Tiny package to ship text files and load them easily.
Author-email: khushi <error404khushi@gmail.com>
License: MIT
Requires-Python: >=3.8
Requires-Dist: chardet
